psengine/__init__.py
psengine/_sdk_id.py
psengine/_version.py
psengine/base_http_client.py
psengine/common_models.py
psengine/constants.py
psengine/endpoints.py
psengine/errors.py
psengine/py.typed
psengine/rf_client.py
psengine/analyst_notes/__init__.py
psengine/analyst_notes/constants.py
psengine/analyst_notes/errors.py
psengine/analyst_notes/helpers.py
psengine/analyst_notes/markdown.py
psengine/analyst_notes/models.py
psengine/analyst_notes/note.py
psengine/analyst_notes/note_mgr.py
psengine/classic_alerts/__init__.py
psengine/classic_alerts/classic_alert.py
psengine/classic_alerts/classic_alert_mgr.py
psengine/classic_alerts/constants.py
psengine/classic_alerts/errors.py
psengine/classic_alerts/helpers.py
psengine/classic_alerts/models.py
psengine/classic_alerts/markdown/__init__.py
psengine/classic_alerts/markdown/markdown.py
psengine/collective_insights/__init__.py
psengine/collective_insights/collective_insights.py
psengine/collective_insights/constants.py
psengine/collective_insights/errors.py
psengine/collective_insights/insight.py
psengine/collective_insights/models.py
psengine/config/__init__.py
psengine/config/config.py
psengine/config/errors.py
psengine/detection/__init__.py
psengine/detection/detection_mgr.py
psengine/detection/detection_rule.py
psengine/detection/errors.py
psengine/detection/helpers.py
psengine/detection/models.py
psengine/enrich/__init__.py
psengine/enrich/constants.py
psengine/enrich/errors.py
psengine/enrich/lookup.py
psengine/enrich/lookup_mgr.py
psengine/enrich/soar.py
psengine/enrich/soar_mgr.py
psengine/enrich/models/__init__.py
psengine/enrich/models/base_enriched_entity.py
psengine/enrich/models/lookup.py
psengine/enrich/models/soar.py
psengine/entity_lists/__init__.py
psengine/entity_lists/constants.py
psengine/entity_lists/entity_list.py
psengine/entity_lists/entity_list_mgr.py
psengine/entity_lists/errors.py
psengine/entity_lists/models.py
psengine/entity_match/__init__.py
psengine/entity_match/entity_match.py
psengine-2.4.2.dist-info/licenses/LICENSE
psengine-2.4.2.dist-info/METADATA
psengine-2.4.2.dist-info/WHEEL
psengine-2.4.2.dist-info/top_level.txt
psengine-2.4.2.dist-info/RECORD
